MiraAiSystems/MasterFunctions.py
MiraAiSystems/__init__.py
miraaisystems-0.2.0.dist-info/METADATA
miraaisystems-0.2.0.dist-info/WHEEL
miraaisystems-0.2.0.dist-info/top_level.txt
miraaisystems-0.2.0.dist-info/RECORD
