Metadata-Version: 2.4
Name: MiraAiSystems
Version: 0.2.0
Summary: An AI system that uses Gemini AI to do various tasks including NLP, file operations, and media handling.
Author: MoonTech
Classifier: Programming Language :: Python :: 3
Classifier: Operating System :: OS Independent
Requires-Python: >=3.7
Requires-Dist: python-dotenv
Requires-Dist: google-generativeai
Requires-Dist: rich
Requires-Dist: ultralytics
Requires-Dist: pyttsx3
Requires-Dist: SpeechRecognition
Requires-Dist: PyAudio
Requires-Dist: Pillow
Requires-Dist: PyPDF2
Requires-Dist: mutagen
Requires-Dist: pygame
Dynamic: author
Dynamic: classifier
Dynamic: description
Dynamic: description-content-type
Dynamic: requires-dist
Dynamic: requires-python
Dynamic: summary
